{
	"name": "AzurePostgreSqlTable16",
	"properties": {
		"linkedServiceName": {
			"referenceName": "AzurePostgreSql1",
			"type": "LinkedServiceReference"
		},
		"folder": {
			"name": "ds_Nishrita"
		},
		"annotations": [],
		"type": "AzurePostgreSqlTable",
		"schema": [
			{
				"name": "employee_id",
				"type": "integer",
				"precision": 0,
				"scale": 0
			},
			{
				"name": "employee_name",
				"type": "character varying",
				"precision": 0,
				"scale": 0
			},
			{
				"name": "department",
				"type": "character varying",
				"precision": 0,
				"scale": 0
			},
			{
				"name": "salary",
				"type": "integer",
				"precision": 0,
				"scale": 0
			},
			{
				"name": "hire_date",
				"type": "date",
				"precision": 0,
				"scale": 0
			},
			{
				"name": "start_date",
				"type": "timestamp without time zone",
				"precision": 0,
				"scale": 0
			},
			{
				"name": "end_date",
				"type": "timestamp without time zone",
				"precision": 0,
				"scale": 0
			},
			{
				"name": "current_flag",
				"type": "character varying",
				"precision": 0,
				"scale": 0
			},
			{
				"name": "row_count",
				"type": "integer",
				"precision": 0,
				"scale": 0
			}
		],
		"typeProperties": {
			"schema": "nishrita",
			"table": "employee"
		}
	},
	"type": "Microsoft.DataFactory/factories/datasets"
}